afdoededk/retrieve.py
doegnrapporter/__init__.py
doegnrapporter/retrieve.py
domstoldk/__init__.py
domstoldk/dst-afg-ger9.csv
domstoldk/retrieve.py
__init__.py
base.py
scrapers_for_journalists-0.1.7.dist-info/METADATA
scrapers_for_journalists-0.1.7.dist-info/WHEEL
scrapers_for_journalists-0.1.7.dist-info/RECORD
