Metadata-Version: 2.3
Name: scrapers_for_journalists
Version: 0.1.7
Summary: Scrapers that helps journalists at Kristeligt Dagblad
Author: MadsLang
Author-email: lang@k.dk
Requires-Python: >=3.10,<4.0
Classifier: Programming Language :: Python :: 3
Classifier: Programming Language :: Python :: 3.10
Classifier: Programming Language :: Python :: 3.11
Classifier: Programming Language :: Python :: 3.12
Classifier: Programming Language :: Python :: 3.13
Requires-Dist: bs4 (>=0.0.2,<0.0.3)
Requires-Dist: lxml (>=5.2.2,<6.0.0)
Requires-Dist: openpyxl (>=3.1.5,<4.0.0)
Requires-Dist: pandas (>=2.1.2,<2.2)
Requires-Dist: requests (>=2.24.0)
Requires-Dist: tqdm (>=4.66.4,<5.0.0)
